LICENSE
MANIFEST.in
README.md
pyproject.toml
setup.cfg
setup.py
counter_widgets/__init__.py
counter_widgets/widgets.py
counter_widgets/static/counter_widgets/js/counter.js
counter_widgets/templates/counter_widgets/counter.html
django_counter_widget.egg-info/PKG-INFO
django_counter_widget.egg-info/SOURCES.txt
django_counter_widget.egg-info/dependency_links.txt
django_counter_widget.egg-info/requires.txt
django_counter_widget.egg-info/top_level.txt