Metadata-Version: 2.1
Name: django-counter-widget
Version: 1.1
Summary: A Django counter widget
Home-page: https://github.com/AbdullahSaquib/django-counter-widget
Author: Abdullah Saquib
Author-email: abdullahsaquib@gmail.com
License: MIT License
Platform: UNKNOWN
Classifier: Environment :: Web Environment
Classifier: Framework :: Django
Classifier: Framework :: Django :: 4.0
Classifier: Intended Audience :: Developers
Classifier: Operating System :: OS Independent
Classifier: Programming Language :: Python :: 3
Requires-Python: >=3.8
